niho/__init__.py
niho-1.0.0.dist-info/METADATA
niho-1.0.0.dist-info/WHEEL
niho-1.0.0.dist-info/top_level.txt
niho-1.0.0.dist-info/RECORD
