Metadata-Version: 2.1
Name: niho
Version: 1.0.0
Summary: Niho is a simple HTTP server framework.
Author: Nihad Kerimli
Classifier: Programming Language :: Python :: 3
Classifier: License :: OSI Approved :: MIT License
Classifier: Operating System :: OS Independent
Requires-Python: >=3.7
